toml_config/__init__.py
toml_config/core.py
toml_config-0.1.3.dist-info/LICENSE.txt
toml_config-0.1.3.dist-info/METADATA
toml_config-0.1.3.dist-info/WHEEL
toml_config-0.1.3.dist-info/top_level.txt
toml_config-0.1.3.dist-info/RECORD
