Metadata-Version: 2.1
Name: toml_config
Version: 0.1.3
Summary: Python library that simplifies parsing and creating Toml configuration files.
Home-page: https://github.com/SemenovAV/toml_config
Author: SemenovAV
Author-email: 7.on.off@bk.ru
License: MIT
Platform: UNKNOWN
Classifier: Programming Language :: Python :: 3
Classifier: License :: OSI Approved :: MIT License
Classifier: Operating System :: OS Independent
